observant/__init__.py
observant/observable.py
observant/observable_dict.py
observant/observable_list.py
observant/observable_proxy.py
observant/py.typed
observant/undoable_observable.py
observant/interfaces/__init__.py
observant/interfaces/dict.py
observant/interfaces/list.py
observant/interfaces/observable.py
observant/interfaces/proxy.py
observant/types/__init__.py
observant/types/collection_change_type.py
observant/types/dict_change.py
observant/types/list_change.py
observant/types/proxy_field_key.py
observant/types/undo_config.py
observant-0.1.7.dist-info/licenses/LICENSE
observant-0.1.7.dist-info/METADATA
observant-0.1.7.dist-info/WHEEL
observant-0.1.7.dist-info/top_level.txt
observant-0.1.7.dist-info/RECORD
