Metadata-Version: 2.4
Name: observant
Version: 0.1.7
Summary: Type-safe observables and proxies for building reactive Python applications.
Author-email: Mrowr Purr <mrowr.purr@gmail.com>
License-Expression: 0BSD
Project-URL: Documentation, https://mrowrlib.github.io/observant.py
Project-URL: Homepage, https://mrowrlib.github.io/observant.py
Project-URL: Repository, https://github.com/MrowrLib/observant.py
Keywords: observable,reactive programming,data binding,state management,python reactive,undo redo,computed properties,python state
Classifier: Programming Language :: Python :: 3
Classifier: Programming Language :: Python :: 3.12
Classifier: Operating System :: OS Independent
Requires-Python: >=3.12
License-File: LICENSE
Dynamic: license-file
